[
    {
        "name": "MBTA Rapid Transit",
        "description": "Boston Subway System Lines and Stops",
        "category": "transportation",
        "city": "Boston, MA",
        "raw_data_type": "shape_file_archive",
        "url": "https://data.kitware.com/api/v1/item/64907b20f04fb368544295e4/download",
        "path": "boston/mbta_rapid_transit.zip",
        "style": {
            "property_map": {
                "colors": "LINE"
            },
            "options": {
                "color_delimiter": "/",
                "outline": "white"
            }
        }
    },
    {
        "name": "MBTA Commuter Rail",
        "description": "Rail linework and station points for passenger, freight, and Amtrak and MBTA Commuter Rail trains.",
        "category": "transportation",
        "city": "Boston, MA",
        "raw_data_type": "shape_file_archive",
        "url": "https://data.kitware.com/api/v1/item/64907c77f04fb368544295ed/download",
        "path": "boston/commuter_rail.zip",
        "style": {
            "property_map": {
                "colors": "gray"
            },
            "options": {
                "outline": "black"
            }
        }
    },
    {
        "name": "Hurricane Surge Inundation Zones",
        "description": "This layer represents worst-case Hurricane Surge Inundation areas for Category 1 through 4 hurricanes striking the coast of Massachusetts.",
        "category": "climate",
        "city": "Boston, MA",
        "raw_data_type": "shape_file_archive",
        "url": "https://data.kitware.com/api/v1/item/64907b6ef04fb368544295e7/download",
        "path": "boston/hurr_inun.zip",
        "style": {
            "property_map": {
                "colors": "HURR_CAT"
            },
            "options": {
                "palette": {
                    "1": "powderblue",
                    "2": "deepskyblue",
                    "3": "royalblue",
                    "4": "mediumblue",
                    "5": "darkblue"
                }
            }
        }
    },
    {
        "name": "FEMA National Flood Hazard",
        "description": "The National Flood Hazard Layer (NFHL) dataset represents the current effective flood risk data for those parts of the country where maps have been modernized by the Federal Emergency Management Agency (FEMA).",
        "category": "climate",
        "city": "Boston, MA",
        "raw_data_type": "shape_file_archive",
        "url": "https://data.kitware.com/api/v1/item/64907beff04fb368544295ea/download",
        "path": "boston/flood_hazard_fema.zip",
        "network": true,
        "style": {
            "property_map": {
                "colors": "FLD_ZONE"
            },
            "options": {
                "palette": {
                    "A": "gold",
                    "AE": "orange",
                    "AH": "tomato",
                    "AO": "orangered",
                    "VE": "darkred",
                    "D": "gray",
                    "X": "green"
                }
            }
        }
    },
    {
        "name": "Massachusetts Elevation Data",
        "description": "Low resolution sampling of land elevation in meters above sea level",
        "category": "elevation",
        "city": "Boston, MA",
        "raw_data_type": "cloud_optimized_geotiff",
        "url": "https://data.kitware.com/api/v1/item/64907e4df04fb368544295f0/download",
        "path": "boston/easternmass.tif",
        "network": true,
        "style": {
            "options": {
                "transparency_threshold": 0,
                "trim_distribution_percentage": 0.01
            }
        }
    }
]
